azure/mgmt/resourcegraph/__init__.py
azure/mgmt/resourcegraph/_configuration.py
azure/mgmt/resourcegraph/_resource_graph_client.py
azure/mgmt/resourcegraph/_version.py
azure/mgmt/resourcegraph/aio/__init__.py
azure/mgmt/resourcegraph/aio/_configuration.py
azure/mgmt/resourcegraph/aio/_resource_graph_client.py
azure/mgmt/resourcegraph/aio/operations/__init__.py
azure/mgmt/resourcegraph/aio/operations/_operations.py
azure/mgmt/resourcegraph/aio/operations/_resource_graph_client_operations.py
azure/mgmt/resourcegraph/models/__init__.py
azure/mgmt/resourcegraph/models/_models.py
azure/mgmt/resourcegraph/models/_models_py3.py
azure/mgmt/resourcegraph/models/_resource_graph_client_enums.py
azure/mgmt/resourcegraph/operations/__init__.py
azure/mgmt/resourcegraph/operations/_operations.py
azure/mgmt/resourcegraph/operations/_resource_graph_client_operations.py
azure_mgmt_resourcegraph-8.0.0.dist-info/METADATA
azure_mgmt_resourcegraph-8.0.0.dist-info/WHEEL
azure_mgmt_resourcegraph-8.0.0.dist-info/top_level.txt
azure_mgmt_resourcegraph-8.0.0.dist-info/RECORD
